mllm_shap/__init__.py
mllm_shap/connectors/__init__.py
mllm_shap/connectors/base/__init__.py
mllm_shap/connectors/base/_validators.py
mllm_shap/connectors/base/audio.py
mllm_shap/connectors/base/chat.py
mllm_shap/connectors/base/chat_entry.py
mllm_shap/connectors/base/explainer_cache.py
mllm_shap/connectors/base/filters.py
mllm_shap/connectors/base/model.py
mllm_shap/connectors/base/model_response.py
mllm_shap/connectors/config.py
mllm_shap/connectors/enums.py
mllm_shap/connectors/filters.py
mllm_shap/connectors/liquid/__init__.py
mllm_shap/connectors/liquid/chat.py
mllm_shap/connectors/liquid/config.py
mllm_shap/connectors/liquid/model.py
mllm_shap/connectors/mock/__init__.py
mllm_shap/connectors/mock/chat.py
mllm_shap/connectors/mock/config.py
mllm_shap/connectors/mock/model.py
mllm_shap/connectors/transformers_text/__init__.py
mllm_shap/connectors/transformers_text/chat.py
mllm_shap/connectors/transformers_text/config.py
mllm_shap/connectors/transformers_text/model.py
mllm_shap/shap/__init__.py
mllm_shap/shap/base/__init__.py
mllm_shap/shap/base/_cache_manager.py
mllm_shap/shap/base/_generate_responses.py
mllm_shap/shap/base/_mask_generator.py
mllm_shap/shap/base/_masks_manager.py
mllm_shap/shap/base/_validators.py
mllm_shap/shap/base/approx.py
mllm_shap/shap/base/complementary.py
mllm_shap/shap/base/embeddings.py
mllm_shap/shap/base/explainer.py
mllm_shap/shap/base/normalizers.py
mllm_shap/shap/base/shap_explainer.py
mllm_shap/shap/base/similarity.py
mllm_shap/shap/compact.py
mllm_shap/shap/complementary/__init__.py
mllm_shap/shap/complementary/_base.py
mllm_shap/shap/complementary/limited.py
mllm_shap/shap/complementary/standard.py
mllm_shap/shap/embeddings.py
mllm_shap/shap/enums.py
mllm_shap/shap/explainer_result.py
mllm_shap/shap/hierarchical/__init__.py
mllm_shap/shap/hierarchical/enums.py
mllm_shap/shap/hierarchical/explainer.py
mllm_shap/shap/hierarchical/graph.py
mllm_shap/shap/monte_carlo/__init__.py
mllm_shap/shap/monte_carlo/_base.py
mllm_shap-0.1.9.dist-info/WHEEL
mllm_shap-0.1.9.dist-info/METADATA
mllm_shap-0.1.9.dist-info/RECORD
